aptest/__init__.py
aptest/mcl2map.py
aptest/prepare_from_contig.py
aptest/cluster/__init__.py
aptest/cluster/adj_ap.py
aptest/cluster/apcluster.py
aptest/cluster/calscore.py
aptest/cluster/ctgconnect.py
aptest/cluster/final.py
aptest/cluster/mergecluster.py
aptest/cluster/runap.py
aptest/cluster/runmcl.py
aptest/exec/__init__.py
aptest/exec/maincluster.py
aptest/newscore/__init__.py
aptest/newscore/ratiosim.py
aptest/scripts/phypertest.R
aptest/utils/__init__.py
aptest/utils/check.py
aptest/utils/protein_mcl.py
aptest-1.1.0.dist-info/LICENSE
aptest-1.1.0.dist-info/METADATA
aptest-1.1.0.dist-info/WHEEL
aptest-1.1.0.dist-info/entry_points.txt
aptest-1.1.0.dist-info/top_level.txt
aptest-1.1.0.dist-info/RECORD
