Metadata-Version: 2.1
Name: aptest
Version: 1.1.0
Home-page: https://github.com/hbyaoherbert/Apclusterv.git
Author: haobinherbert
Author-email: haobinherbert@163.com
License: Apache
Classifier: License :: OSI Approved :: Apache Software License
Classifier: Natural Language :: English
Classifier: Operating System :: Unix
Classifier: Programming Language :: Python
Classifier: Programming Language :: Python :: 3.7
Classifier: Topic :: Software Development :: Libraries :: Python Modules
Requires-Python: >=3.7
License-File: LICENSE
Requires-Dist: pandas (>=0.18.0)
Requires-Dist: numpy (>=1.9.2)
